Metadata-Version: 1.0
Name: django-unrest-comments
Version: 0.1.0
Summary: Threaded ajax comments using django on the back end and riot/unrest on the front.
Home-page: https://github.com/chriscauley/django-unrest-comments/archive/v0.1.0.tar.gz
Author: chriscauley
Author-email: UNKNOWN
License: UNKNOWN
Keywords: django,comments,threaded comments
Platform: UNKNOWN
